filters_django/__init__.py
filters_django-1.0.5.dist-info/DESCRIPTION.rst
filters_django-1.0.5.dist-info/METADATA
filters_django-1.0.5.dist-info/RECORD
filters_django-1.0.5.dist-info/WHEEL
filters_django-1.0.5.dist-info/entry_points.txt
filters_django-1.0.5.dist-info/metadata.json
filters_django-1.0.5.dist-info/top_level.txt
