Metadata-Version: 1.1
Name: filters-django
Version: 1.0.5
Summary: Adds filters for Django-specific features.
Home-page: https://filters.readthedocs.io/
Author: Phoenix Zerin
Author-email: phoenix.zerin@eflglobal.com
License: MIT
Keywords: data validation,django
Platform: UNKNOWN
Classifier: Development Status :: 5 - Production/Stable
Classifier: Intended Audience :: Developers
Classifier: License :: OSI Approved :: MIT License
Classifier: Programming Language :: Python :: 2
Classifier: Programming Language :: Python :: 2.7
Classifier: Programming Language :: Python :: 3
Classifier: Programming Language :: Python :: 3.5
Classifier: Programming Language :: Python :: 3.6
Classifier: Topic :: Software Development :: Libraries :: Python Modules
Classifier: Topic :: Text Processing :: Filters
